{
    "/stages/:missionId/:stageId": "/stages?stageId=:missionId:stageId&_expand=mission",
    "/stages/times/:stageId": "/times?&stageId=:stageId&_expand=mission&_expand=stage&_expand=user&_sort=time&_order=asc",
    "/stages/times/:stageId/top": "/times?stageId=:stageId&_expand=mission&_expand=stage&_expand=user&_sort=time&_order=asc&_limit=1",
    "/stages/times/:stageId/user/:userId": "/times?userId=:userId&stageId=:stageId&_expand=mission&_expand=stage&_expand=user&_sort=time&_order=asc",
    "/stages/times/:stageId/user/:userId/top": "/times?userId=:userId&stageId=:stageId&_expand=mission&_expand=stage&_expand=user&_sort=time&_order=asc&_limit=1",
    "/missions/:missionId": "/missions?id=:missionId",
    "/missions/:missionId/stages": "/stages?missionId=:missionId",
    "/users/:userId": "/users?id=:userId",
    "/users/:userId/times": "/times?userId=:userId",
    "/users/:userId/times/:missionId/:stageId": "/times?userId=:userId&stageId=:missionId:stageId&_expand=mission&_expand=stage&_expand=user"
}